twep/__init__.py
twep-0.0.11.dist-info/METADATA
twep-0.0.11.dist-info/WHEEL
twep-0.0.11.dist-info/top_level.txt
twep-0.0.11.dist-info/RECORD
