Metadata-Version: 2.1
Name: twep
Version: 0.0.11
Summary: Multitask time-series forecasting
Home-page: UNKNOWN
Author: Aiola Labs
Author-email: 
License: UNKNOWN
Platform: UNKNOWN
Requires-Python: >=3.5
Requires-Dist: numpy (>=1.19.1)
